{
  "_class": "group",
  "do_objectID": "E133C787-6A8B-4E7D-9FB8-9661B364EBCE",
  "exportOptions": {
    "_class": "exportOptions",
    "do_objectID": "2F1B9A52-C6D5-4858-A7AA-01439F1DFE65",
    "exportFormats": [
    ],
    "includedLayerIds": [
    ],
    "layerOptions": 0,
    "shouldTrim": false
  },
  "frame": {
    "_class": "rect",
    "constrainProportions": false,
    "do_objectID": "5BF9E6BF-CA0A-46B4-8F1A-3123B478D1A9",
    "height": 117,
    "width": 756,
    "x": 0,
    "y": 435
  },
  "hasClickThrough": false,
  "isFlippedHorizontal": false,
  "isFlippedVertical": false,
  "isLocked": false,
  "isVisible": true,
  "layerListExpandedType": 1,
  "layers": [
    {
      "class": "shapeGroup",
      "id": "F745596F-F6D8-46DE-BCE5-90637296909E"
    },
    {
      "class": "text",
      "id": "2024C6C0-D659-457A-9045-C155CC7DB1E6"
    },
    {
      "class": "text",
      "id": "48436F50-3F98-42B8-AB30-F60C3532EA81"
    },
    {
      "class": "group",
      "id": "CECE544C-F8B3-4196-A771-307C4EDA9BFE"
    },
    {
      "class": "text",
      "id": "601D6A49-DB87-4A4F-9233-E948270278AC"
    },
    {
      "class": "group",
      "id": "DC893A41-43F4-4960-B261-B78CBD22D3C8"
    }
  ],
  "name": "Group 2",
  "nameIsFixed": false,
  "resizingConstraint": 63,
  "resizingType": 0,
  "rotation": 0,
  "shouldBreakMaskChain": false,
  "style": {
    "_class": "style",
    "do_objectID": "6957C096-F671-4A2D-83FC-B87E2B5D0224",
    "endDecorationType": 0,
    "miterLimit": 10,
    "startDecorationType": 0
  }
}