{
  "_class": "shapeGroup",
  "clippingMaskMode": 0,
  "do_objectID": "2FC602F8-B036-4FC1-A4D6-0F90997987BA",
  "exportOptions": {
    "_class": "exportOptions",
    "do_objectID": "41B8C8A1-ED1F-4BEF-A2A5-CE0A6C2E1653",
    "exportFormats": [
    ],
    "includedLayerIds": [
    ],
    "layerOptions": 0,
    "shouldTrim": false
  },
  "frame": {
    "_class": "rect",
    "constrainProportions": false,
    "do_objectID": "18BC4AB6-848F-4403-B49F-C2BBBBE1534A",
    "height": 13.33333333333333,
    "width": 13.33333333333333,
    "x": 1.333333333333333,
    "y": 1.333333333333333
  },
  "hasClickThrough": false,
  "hasClippingMask": false,
  "isFlippedHorizontal": false,
  "isFlippedVertical": false,
  "isLocked": false,
  "isVisible": true,
  "layerListExpandedType": 1,
  "layers": [
    {
      "class": "shapePath",
      "id": "441C5D7E-B7C2-441A-B5A4-3E7B1CD0F786"
    },
    {
      "class": "shapePath",
      "id": "D2128FF3-A080-4C63-B098-FBE96AC9D14E"
    }
  ],
  "name": "Shape",
  "nameIsFixed": false,
  "resizingConstraint": 63,
  "resizingType": 0,
  "rotation": 0,
  "shouldBreakMaskChain": false,
  "style": {
    "_class": "style",
    "do_objectID": "D30987AE-B636-4563-89CF-F6CAFBB85476",
    "endDecorationType": 0,
    "fills": [
      {
        "_class": "fill",
        "color": {
          "_class": "color",
          "alpha": 1,
          "blue": 0.4980392156862745,
          "green": 0.7764705882352941,
          "red": 0.2431372549019608
        },
        "fillType": 0,
        "isEnabled": true,
        "noiseIndex": 0,
        "noiseIntensity": 0,
        "patternFillType": 1,
        "patternTileScale": 1
      }
    ],
    "miterLimit": 10,
    "startDecorationType": 0
  },
  "windingRule": 0
}